dendri/__init__.py
dendri/_version.py
dendri/conftest.py
dendri/dataframe.py
dendri/dates.py
dendri/utils.py
dendri-0.2.2.dist-info/LICENSE
dendri-0.2.2.dist-info/METADATA
dendri-0.2.2.dist-info/WHEEL
dendri-0.2.2.dist-info/top_level.txt
dendri-0.2.2.dist-info/RECORD
