Metadata-Version: 2.1
Name: dendri
Version: 0.2.2
Summary: Library for common healthcare related algorithms.
Home-page: https://github.com/Naissant/dendri
Author: Dendri Authors
Author-email: wesr000@gmail.com
License: MIT
Classifier: Development Status :: 2 - Pre-Alpha
Classifier: Intended Audience :: Healthcare Industry
Classifier: License :: OSI Approved :: MIT License
Classifier: Natural Language :: English
Classifier: Operating System :: OS Independent
Classifier: Programming Language :: Python :: 3.7
Requires-Python: >=3.7
License-File: LICENSE
Requires-Dist: pyspark (>=3.1.1)
Requires-Dist: python-dateutil
Provides-Extra: dev
Requires-Dist: pytest ; extra == 'dev'
Requires-Dist: black ; extra == 'dev'
Requires-Dist: flake8 ; extra == 'dev'
Requires-Dist: pre-commit ; extra == 'dev'
